LICENSE
README.md
setup.cfg
setup.py
algorithm/__init__.py
algorithm/node.py
algorithm/routing_algorithm.py
routing_programming.egg-info/PKG-INFO
routing_programming.egg-info/SOURCES.txt
routing_programming.egg-info/dependency_links.txt
routing_programming.egg-info/top_level.txt