Metadata-Version: 2.1
Name: routing_programming
Version: 0.0.2
Summary: A routing algorithm for optimizing paths and schedules in logistics and transportation.
Home-page: https://github.com/JulianD1997/routing_algorithm.git
Author: Julian Casallas
Author-email: julian.casallasb@gmail.com
License: MIT
License-File: LICENSE
